aiddl_external_grpc_python/__init__.py
aiddl_external_grpc_python/converter.py
aiddl_external_grpc_python/actor/__init__.py
aiddl_external_grpc_python/actor/actor_client.py
aiddl_external_grpc_python/actor/actor_server.py
aiddl_external_grpc_python/container/__init__.py
aiddl_external_grpc_python/container/container_server.py
aiddl_external_grpc_python/container/grpc_function.py
aiddl_external_grpc_python/function/__init__.py
aiddl_external_grpc_python/function/function_client.py
aiddl_external_grpc_python/function/function_server.py
aiddl_external_grpc_python/generated/__init__.py
aiddl_external_grpc_python/generated/actor_pb2.py
aiddl_external_grpc_python/generated/actor_pb2_grpc.py
aiddl_external_grpc_python/generated/aiddl_pb2.py
aiddl_external_grpc_python/generated/aiddl_pb2_grpc.py
aiddl_external_grpc_python/generated/container_pb2.py
aiddl_external_grpc_python/generated/container_pb2_grpc.py
aiddl_external_grpc_python/generated/empty_pb2.py
aiddl_external_grpc_python/generated/empty_pb2_grpc.py
aiddl_external_grpc_python/generated/function_pb2.py
aiddl_external_grpc_python/generated/function_pb2_grpc.py
aiddl_external_grpc_python/generated/receiver_pb2.py
aiddl_external_grpc_python/generated/receiver_pb2_grpc.py
aiddl_external_grpc_python/generated/sender_pb2.py
aiddl_external_grpc_python/generated/sender_pb2_grpc.py
aiddl_external_grpc_python/generated/sensor_pb2.py
aiddl_external_grpc_python/generated/sensor_pb2_grpc.py
aiddl_external_grpc_python/receiver/__init__.py
aiddl_external_grpc_python/receiver/receiver_client.py
aiddl_external_grpc_python/receiver/receiver_server.py
aiddl_external_grpc_python/sender/__init__.py
aiddl_external_grpc_python/sender/sender_client.py
aiddl_external_grpc_python/sender/sender_server.py
aiddl_external_grpc_python/sensor/__init__.py
aiddl_external_grpc_python/sensor/sensor_client.py
aiddl_external_grpc-0.2.2.dist-info/LICENSE
aiddl_external_grpc-0.2.2.dist-info/METADATA
aiddl_external_grpc-0.2.2.dist-info/WHEEL
aiddl_external_grpc-0.2.2.dist-info/top_level.txt
aiddl_external_grpc-0.2.2.dist-info/RECORD
