Metadata-Version: 2.1
Name: aiddl-external-grpc
Version: 0.2.2
Summary: gRPC Services for the AI Domain Definition Langauge (AIDDL) Framework
Home-page: http://www.aiddl.org
Author: Uwe Köckemann
Author-email: uwe.kockemann@oru.se
Project-URL: Bug Tracker, https://github.com/uwe-koeckemann/AIDDL/issues
Classifier: Programming Language :: Python :: 3
Classifier: License :: OSI Approved :: MIT License
Classifier: Operating System :: OS Independent
Requires-Python: >=3.7
License-File: LICENSE
Requires-Dist: aiddl-core (>=0.3.0)
Requires-Dist: unified-planning (>=0.5.0)
Requires-Dist: grpcio (==1.51.3)
Requires-Dist: grpcio-tools (==1.51.3)
